Metadata-Version: 2.1
Name: tomilliseconds
Version: 1.0.1
Summary: Convert an object of time properties to milliseconds: {'seconds': 10} → 10000
Home-page: https://yoginth.com
Author: Yoginth
Author-email: me@yoginth.com
License: UNKNOWN
Project-URL: Patreon, https://www.patreon.com/yoginth
Project-URL: Source, https://gitlab.com/yoginth/tomilliseconds
Platform: UNKNOWN
Classifier: Programming Language :: Python
Classifier: Natural Language :: English
Classifier: Environment :: Plugins
Classifier: Operating System :: OS Independent
Classifier: Intended Audience :: Developers
Classifier: License :: OSI Approved :: MIT License
